<?xml version="1.0" encoding="UTF-8" standalone="yes"?>
<types>
	<type name="RS6_Avant_bumper_front">
		<nominal>0</nominal>
		<lifetime>3888000</lifetime>
		<restock>0</restock>
		<min>0</min>
		<quantmin>-1</quantmin>
		<quantmax>-1</quantmax>
		<cost>100</cost>
		<flags count_in_cargo="0" count_in_hoarder="0" count_in_map="1" count_in_player="0" crafted="0" deloot="0"/>
	</type>
	<type name="RS6_Avant_bumper_Rust">
		<nominal>0</nominal>
		<lifetime>3888000</lifetime>
		<restock>0</restock>
		<min>0</min>
		<quantmin>-1</quantmin>
		<quantmax>-1</quantmax>
		<cost>100</cost>
		<flags count_in_cargo="0" count_in_hoarder="0" count_in_map="1" count_in_player="0" crafted="0" deloot="0"/>
	</type>	
	<type name="RS6_Avant_bumper_Samoa_Orang">
		<nominal>0</nominal>
		<lifetime>3888000</lifetime>
		<restock>0</restock>
		<min>0</min>
		<quantmin>-1</quantmin>
		<quantmax>-1</quantmax>
		<cost>100</cost>
		<flags count_in_cargo="0" count_in_hoarder="0" count_in_map="1" count_in_player="0" crafted="0" deloot="0"/>
	</type>
	<type name="RS6_Avant_bumper_Camo_Blue">
		<nominal>0</nominal>
		<lifetime>3888000</lifetime>
		<restock>0</restock>
		<min>0</min>
		<quantmin>-1</quantmin>
		<quantmax>-1</quantmax>
		<cost>100</cost>
		<flags count_in_cargo="0" count_in_hoarder="0" count_in_map="1" count_in_player="0" crafted="0" deloot="0"/>
	</type>	
	<type name="RS6_Avant_bumper_Camo_Pink">
		<nominal>0</nominal>
		<lifetime>3888000</lifetime>
		<restock>0</restock>
		<min>0</min>
		<quantmin>-1</quantmin>
		<quantmax>-1</quantmax>
		<cost>100</cost>
		<flags count_in_cargo="0" count_in_hoarder="0" count_in_map="1" count_in_player="0" crafted="0" deloot="0"/>
	</type>		
	<type name="RS6_Avant_bumper_Camo_White">
		<nominal>0</nominal>
		<lifetime>3888000</lifetime>
		<restock>0</restock>
		<min>0</min>
		<quantmin>-1</quantmin>
		<quantmax>-1</quantmax>
		<cost>100</cost>
		<flags count_in_cargo="0" count_in_hoarder="0" count_in_map="1" count_in_player="0" crafted="0" deloot="0"/>
	</type>		
	<type name="RS6_Avant_bumper_rear">
		<nominal>0</nominal>
		<lifetime>3888000</lifetime>
		<restock>0</restock>
		<min>0</min>
		<quantmin>-1</quantmin>
		<quantmax>-1</quantmax>
		<cost>100</cost>
		<flags count_in_cargo="0" count_in_hoarder="0" count_in_map="1" count_in_player="0" crafted="0" deloot="0"/>
	</type>		
	<type name="RS6_Avant_bumper_Rust">
		<nominal>0</nominal>
		<lifetime>3888000</lifetime>
		<restock>0</restock>
		<min>0</min>
		<quantmin>-1</quantmin>
		<quantmax>-1</quantmax>
		<cost>100</cost>
		<flags count_in_cargo="0" count_in_hoarder="0" count_in_map="1" count_in_player="0" crafted="0" deloot="0"/>
	</type>		
	<type name="RS6_Avant_bumper_rear_Samoa_Orange">
		<nominal>0</nominal>
		<lifetime>3888000</lifetime>
		<restock>0</restock>
		<min>0</min>
		<quantmin>-1</quantmin>
		<quantmax>-1</quantmax>
		<cost>100</cost>
		<flags count_in_cargo="0" count_in_hoarder="0" count_in_map="1" count_in_player="0" crafted="0" deloot="0"/>
	</type>		
	<type name="RS6_Avant_bumper_Camo_Blue">
		<nominal>0</nominal>
		<lifetime>3888000</lifetime>
		<restock>0</restock>
		<min>0</min>
		<quantmin>-1</quantmin>
		<quantmax>-1</quantmax>
		<cost>100</cost>
		<flags count_in_cargo="0" count_in_hoarder="0" count_in_map="1" count_in_player="0" crafted="0" deloot="0"/>
	</type>	
	<type name="RS6_Avant_bumper_Camo_Pink">
		<nominal>0</nominal>
		<lifetime>3888000</lifetime>
		<restock>0</restock>
		<min>0</min>
		<quantmin>-1</quantmin>
		<quantmax>-1</quantmax>
		<cost>100</cost>
		<flags count_in_cargo="0" count_in_hoarder="0" count_in_map="1" count_in_player="0" crafted="0" deloot="0"/>
	</type>		
	<type name="RS6_Avant_bumper_Camo_White">
		<nominal>0</nominal>
		<lifetime>3888000</lifetime>
		<restock>0</restock>
		<min>0</min>
		<quantmin>-1</quantmin>
		<quantmax>-1</quantmax>
		<cost>100</cost>
		<flags count_in_cargo="0" count_in_hoarder="0" count_in_map="1" count_in_player="0" crafted="0" deloot="0"/>
	</type>	
	<type name="RS6_Avant_doors_Driver">
		<nominal>0</nominal>
		<lifetime>7200</lifetime>
		<restock>600</restock>
		<min>0</min>
		<quantmin>-1</quantmin>
		<quantmax>-1</quantmax>
		<cost>100</cost>
		<flags count_in_cargo="0" count_in_hoarder="0" count_in_map="1" count_in_player="0" crafted="0" deloot="0"/>
	</type>	
	<type name="RS6_Avant_Doors_coDriver">
		<nominal>0</nominal>
		<lifetime>7200</lifetime>
		<restock>600</restock>
		<min>0</min>
		<quantmin>-1</quantmin>
		<quantmax>-1</quantmax>
		<cost>100</cost>
		<flags count_in_cargo="0" count_in_hoarder="0" count_in_map="1" count_in_player="0" crafted="0" deloot="0"/>
	</type>	
	<type name="RS6_Avant_Doors_coDriver_Rust">
		<nominal>0</nominal>
		<lifetime>7200</lifetime>
		<restock>600</restock>
		<min>0</min>
		<quantmin>-1</quantmin>
		<quantmax>-1</quantmax>
		<cost>100</cost>
		<flags count_in_cargo="0" count_in_hoarder="0" count_in_map="1" count_in_player="0" crafted="0" deloot="0"/>
	</type>	
	<type name="RS6_Avant_Doors_Rust">
		<nominal>0</nominal>
		<lifetime>7200</lifetime>
		<restock>600</restock>
		<min>0</min>
		<quantmin>-1</quantmin>
		<quantmax>-1</quantmax>
		<cost>100</cost>
		<flags count_in_cargo="0" count_in_hoarder="0" count_in_map="1" count_in_player="0" crafted="0" deloot="0"/>
	</type>	
	<type name="RS6_Avant_doors_Driver_Rust">
		<nominal>0</nominal>
		<lifetime>7200</lifetime>
		<restock>600</restock>
		<min>0</min>
		<quantmin>-1</quantmin>
		<quantmax>-1</quantmax>
		<cost>100</cost>
		<flags count_in_cargo="0" count_in_hoarder="0" count_in_map="1" count_in_player="0" crafted="0" deloot="0"/>
	</type>		
	<type name="RS6_Avant_doors_cargo1">
		<nominal>0</nominal>
		<lifetime>7200</lifetime>
		<restock>600</restock>
		<min>0</min>
		<quantmin>-1</quantmin>
		<quantmax>-1</quantmax>
		<cost>100</cost>
		<flags count_in_cargo="0" count_in_hoarder="0" count_in_map="1" count_in_player="0" crafted="0" deloot="0"/>
	</type>	
	<type name="RS6_Avant_doors_cargo2">
		<nominal>0</nominal>
		<lifetime>7200</lifetime>
		<restock>600</restock>
		<min>0</min>
		<quantmin>-1</quantmin>
		<quantmax>-1</quantmax>
		<cost>100</cost>
		<flags count_in_cargo="0" count_in_hoarder="0" count_in_map="1" count_in_player="0" crafted="0" deloot="0"/>
	</type>		
	<type name="RS6_Avant_doors_cargo1_Rust">
		<nominal>0</nominal>
		<lifetime>7200</lifetime>
		<restock>600</restock>
		<min>0</min>
		<quantmin>-1</quantmin>
		<quantmax>-1</quantmax>
		<cost>100</cost>
		<flags count_in_cargo="0" count_in_hoarder="0" count_in_map="1" count_in_player="0" crafted="0" deloot="0"/>
	</type>	
	<type name="RS6_Avant_doors_cargo2_Rust">
		<nominal>0</nominal>
		<lifetime>7200</lifetime>
		<restock>600</restock>
		<min>0</min>
		<quantmin>-1</quantmin>
		<quantmax>-1</quantmax>
		<cost>100</cost>
		<flags count_in_cargo="0" count_in_hoarder="0" count_in_map="1" count_in_player="0" crafted="0" deloot="0"/>
	</type>		
	<type name="RS6_Avant_doors_Driver_Samoa_Orang">
		<nominal>0</nominal>
		<lifetime>7200</lifetime>
		<restock>600</restock>
		<min>0</min>
		<quantmin>-1</quantmin>
		<quantmax>-1</quantmax>
		<cost>100</cost>
		<flags count_in_cargo="0" count_in_hoarder="0" count_in_map="1" count_in_player="0" crafted="0" deloot="0"/>
	</type>	
	<type name="RS6_Avant_Doors_coDriver_Samoa_Orang">
		<nominal>0</nominal>
		<lifetime>7200</lifetime>
		<restock>600</restock>
		<min>0</min>
		<quantmin>-1</quantmin>
		<quantmax>-1</quantmax>
		<cost>100</cost>
		<flags count_in_cargo="0" count_in_hoarder="0" count_in_map="1" count_in_player="0" crafted="0" deloot="0"/>
	</type>	
	<type name="RS6_Avant_doors_cargo1_Samoa_Orang">
		<nominal>0</nominal>
		<lifetime>7200</lifetime>
		<restock>600</restock>
		<min>0</min>
		<quantmin>-1</quantmin>
		<quantmax>-1</quantmax>
		<cost>100</cost>
		<flags count_in_cargo="0" count_in_hoarder="0" count_in_map="1" count_in_player="0" crafted="0" deloot="0"/>
	</type>	
	<type name="RS6_Avant_doors_cargo2_Samoa_Orang">
		<nominal>0</nominal>
		<lifetime>7200</lifetime>
		<restock>600</restock>
		<min>0</min>
		<quantmin>-1</quantmin>
		<quantmax>-1</quantmax>
		<cost>100</cost>
		<flags count_in_cargo="0" count_in_hoarder="0" count_in_map="1" count_in_player="0" crafted="0" deloot="0"/>
	</type>	
	<type name="RS6_Avant_doors_Driver_Camo_Blue">
		<nominal>0</nominal>
		<lifetime>7200</lifetime>
		<restock>600</restock>
		<min>0</min>
		<quantmin>-1</quantmin>
		<quantmax>-1</quantmax>
		<cost>100</cost>
		<flags count_in_cargo="0" count_in_hoarder="0" count_in_map="1" count_in_player="0" crafted="0" deloot="0"/>
	</type>
	<type name="RS6_Avant_Doors_coDriver_Camo_Blue">
		<nominal>0</nominal>
		<lifetime>7200</lifetime>
		<restock>600</restock>
		<min>0</min>
		<quantmin>-1</quantmin>
		<quantmax>-1</quantmax>
		<cost>100</cost>
		<flags count_in_cargo="0" count_in_hoarder="0" count_in_map="1" count_in_player="0" crafted="0" deloot="0"/>
	</type>	
	<type name="RS6_Avant_doors_cargo1_Camo_Blue">
		<nominal>0</nominal>
		<lifetime>7200</lifetime>
		<restock>600</restock>
		<min>0</min>
		<quantmin>-1</quantmin>
		<quantmax>-1</quantmax>
		<cost>100</cost>
		<flags count_in_cargo="0" count_in_hoarder="0" count_in_map="1" count_in_player="0" crafted="0" deloot="0"/>
	</type>	
	<type name="RS6_Avant_doors_cargo2_Camo_Blue">
		<nominal>0</nominal>
		<lifetime>7200</lifetime>
		<restock>600</restock>
		<min>0</min>
		<quantmin>-1</quantmin>
		<quantmax>-1</quantmax>
		<cost>100</cost>
		<flags count_in_cargo="0" count_in_hoarder="0" count_in_map="1" count_in_player="0" crafted="0" deloot="0"/>
	</type>		
	<type name="RS6_Avant_doors_Driver_Camo_Pink">
		<nominal>0</nominal>
		<lifetime>7200</lifetime>
		<restock>600</restock>
		<min>0</min>
		<quantmin>-1</quantmin>
		<quantmax>-1</quantmax>
		<cost>100</cost>
		<flags count_in_cargo="0" count_in_hoarder="0" count_in_map="1" count_in_player="0" crafted="0" deloot="0"/>
	</type>	
	<type name="RS6_Avant_Doors_coDriver_Camo_Pink">
		<nominal>0</nominal>
		<lifetime>7200</lifetime>
		<restock>600</restock>
		<min>0</min>
		<quantmin>-1</quantmin>
		<quantmax>-1</quantmax>
		<cost>100</cost>
		<flags count_in_cargo="0" count_in_hoarder="0" count_in_map="1" count_in_player="0" crafted="0" deloot="0"/>
	</type>	
	<type name="RS6_Avant_doors_cargo1_Camo_Pink">
		<nominal>0</nominal>
		<lifetime>3888000</lifetime>
		<restock>0</restock>
		<min>0</min>
		<quantmin>-1</quantmin>
		<quantmax>-1</quantmax>
		<cost>100</cost>
		<flags count_in_cargo="0" count_in_hoarder="0" count_in_map="1" count_in_player="0" crafted="0" deloot="0"/>
	</type>	
	<type name="RS6_Avant_doors_cargo2_Camo_Pink">
		<nominal>0</nominal>
		<lifetime>7200</lifetime>
		<restock>600</restock>
		<min>0</min>
		<quantmin>-1</quantmin>
		<quantmax>-1</quantmax>
		<cost>100</cost>
		<flags count_in_cargo="0" count_in_hoarder="0" count_in_map="1" count_in_player="0" crafted="0" deloot="0"/>
	</type>			
	<type name="RS6_Avant_doors_Driver_Camo_White">
		<nominal>0</nominal>
		<lifetime>7200</lifetime>
		<restock>600</restock>
		<min>0</min>
		<quantmin>-1</quantmin>
		<quantmax>-1</quantmax>
		<cost>100</cost>
		<flags count_in_cargo="0" count_in_hoarder="0" count_in_map="1" count_in_player="0" crafted="0" deloot="0"/>
	</type>	
	<type name="RS6_Avant_Doors_coDriver_Camo_White">
		<nominal>0</nominal>
		<lifetime>7200</lifetime>
		<restock>600</restock>
		<min>0</min>
		<quantmin>-1</quantmin>
		<quantmax>-1</quantmax>
		<cost>100</cost>
		<flags count_in_cargo="0" count_in_hoarder="0" count_in_map="1" count_in_player="0" crafted="0" deloot="0"/>
	</type>	
	<type name="RS6_Avant_doors_cargo1_Camo_White">
		<nominal>0</nominal>
		<lifetime>7200</lifetime>
		<restock>600</restock>
		<min>0</min>
		<quantmin>-1</quantmin>
		<quantmax>-1</quantmax>
		<cost>100</cost>
		<flags count_in_cargo="0" count_in_hoarder="0" count_in_map="1" count_in_player="0" crafted="0" deloot="0"/>
	</type>	
	<type name="RS6_Avant_doors_cargo2_Camo_White">
		<nominal>0</nominal>
		<lifetime>7200</lifetime>
		<restock>600</restock>
		<min>0</min>
		<quantmin>-1</quantmin>
		<quantmax>-1</quantmax>
		<cost>100</cost>
		<flags count_in_cargo="0" count_in_hoarder="0" count_in_map="1" count_in_player="0" crafted="0" deloot="0"/>
	</type>		
	<type name="RS6_Avant_doors_hood">
		<nominal>0</nominal>
		<lifetime>7200</lifetime>
		<restock>600</restock>
		<min>0</min>
		<quantmin>-1</quantmin>
		<quantmax>-1</quantmax>
		<cost>100</cost>
		<flags count_in_cargo="0" count_in_hoarder="0" count_in_map="1" count_in_player="0" crafted="0" deloot="0"/>
	</type>	
	<type name="RS6_Avant_hood_Rust">
		<nominal>0</nominal>
		<lifetime>3888000</lifetime>
		<restock>0</restock>
		<min>0</min>
		<quantmin>-1</quantmin>
		<quantmax>-1</quantmax>
		<cost>100</cost>
		<flags count_in_cargo="0" count_in_hoarder="0" count_in_map="1" count_in_player="0" crafted="0" deloot="0"/>
	</type>		
	<type name="RS6_Avant_hood_rear_Samoa_Orange">
		<nominal>0</nominal>
		<lifetime>3888000</lifetime>
		<restock>0</restock>
		<min>0</min>
		<quantmin>-1</quantmin>
		<quantmax>-1</quantmax>
		<cost>100</cost>
		<flags count_in_cargo="0" count_in_hoarder="0" count_in_map="1" count_in_player="0" crafted="0" deloot="0"/>
	</type>		
	<type name="RS6_Avant_hood_Camo_Blue">
		<nominal>0</nominal>
		<lifetime>3888000</lifetime>
		<restock>0</restock>
		<min>0</min>
		<quantmin>-1</quantmin>
		<quantmax>-1</quantmax>
		<cost>100</cost>
		<flags count_in_cargo="0" count_in_hoarder="0" count_in_map="1" count_in_player="0" crafted="0" deloot="0"/>
	</type>	
	<type name="RS6_Avant_hood_Camo_Pink">
		<nominal>0</nominal>
		<lifetime>3888000</lifetime>
		<restock>0</restock>
		<min>0</min>
		<quantmin>-1</quantmin>
		<quantmax>-1</quantmax>
		<cost>100</cost>
		<flags count_in_cargo="0" count_in_hoarder="0" count_in_map="1" count_in_player="0" crafted="0" deloot="0"/>
	</type>	
	<type name="RS6_Avant_hood_Camo_White">
		<nominal>0</nominal>
		<lifetime>3888000</lifetime>
		<restock>0</restock>
		<min>0</min>
		<quantmin>-1</quantmin>
		<quantmax>-1</quantmax>
		<cost>100</cost>
		<flags count_in_cargo="0" count_in_hoarder="0" count_in_map="1" count_in_player="0" crafted="0" deloot="0"/>
	</type>	
	<type name="RS6_Avant_doors_trunk">
		<nominal>0</nominal>
		<lifetime>3888000</lifetime>
		<restock>0</restock>
		<min>0</min>
		<quantmin>-1</quantmin>
		<quantmax>-1</quantmax>
		<cost>100</cost>
		<flags count_in_cargo="0" count_in_hoarder="0" count_in_map="1" count_in_player="0" crafted="0" deloot="0"/>
	</type>	
	<type name="RS6_Avant_trunk_Rust">
		<nominal>0</nominal>
		<lifetime>3888000</lifetime>
		<restock>0</restock>
		<min>0</min>
		<quantmin>-1</quantmin>
		<quantmax>-1</quantmax>
		<cost>100</cost>
		<flags count_in_cargo="0" count_in_hoarder="0" count_in_map="1" count_in_player="0" crafted="0" deloot="0"/>
	</type>		
	<type name="RS6_Avant_trunk_rear_Samoa_Orange">
		<nominal>0</nominal>
		<lifetime>3888000</lifetime>
		<restock>0</restock>
		<min>0</min>
		<quantmin>-1</quantmin>
		<quantmax>-1</quantmax>
		<cost>100</cost>
		<flags count_in_cargo="0" count_in_hoarder="0" count_in_map="1" count_in_player="0" crafted="0" deloot="0"/>
	</type>		
	<type name="RS6_Avant_trunk_Camo_Blue">
		<nominal>0</nominal>
		<lifetime>3888000</lifetime>
		<restock>0</restock>
		<min>0</min>
		<quantmin>-1</quantmin>
		<quantmax>-1</quantmax>
		<cost>100</cost>
		<flags count_in_cargo="0" count_in_hoarder="0" count_in_map="1" count_in_player="0" crafted="0" deloot="0"/>
	</type>	
	<type name="RS6_Avant_trunk_Camo_Pink">
		<nominal>0</nominal>
		<lifetime>3888000</lifetime>
		<restock>0</restock>
		<min>0</min>
		<quantmin>-1</quantmin>
		<quantmax>-1</quantmax>
		<cost>100</cost>
		<flags count_in_cargo="0" count_in_hoarder="0" count_in_map="1" count_in_player="0" crafted="0" deloot="0"/>
	</type>	
	<type name="RS6_Avant_trunk_Camo_White">
		<nominal>0</nominal>
		<lifetime>3888000</lifetime>
		<restock>0</restock>
		<min>0</min>
		<quantmin>-1</quantmin>
		<quantmax>-1</quantmax>
		<cost>100</cost>
		<flags count_in_cargo="0" count_in_hoarder="0" count_in_map="1" count_in_player="0" crafted="0" deloot="0"/>
	</type>	
	<type name="RS6_Avant">
		<nominal>0</nominal>
		<lifetime>3888000</lifetime>
		<restock>0</restock>
		<min>0</min>
		<quantmin>-1</quantmin>
		<quantmax>-1</quantmax>
		<cost>100</cost>
		<flags count_in_cargo="0" count_in_hoarder="0" count_in_map="1" count_in_player="0" crafted="0" deloot="0"/>
	</type>	
	<type name="RS6_Avant_Rust">
		<nominal>0</nominal>
		<lifetime>3888000</lifetime>
		<restock>0</restock>
		<min>0</min>
		<quantmin>-1</quantmin>
		<quantmax>-1</quantmax>
		<cost>100</cost>
		<flags count_in_cargo="0" count_in_hoarder="0" count_in_map="1" count_in_player="0" crafted="0" deloot="0"/>
	</type>		
	<type name="RS6_Avant_Samoa_Orange_Metallic">
		<nominal>0</nominal>
		<lifetime>3888000</lifetime>
		<restock>0</restock>
		<min>0</min>
		<quantmin>-1</quantmin>
		<quantmax>-1</quantmax>
		<cost>100</cost>
		<flags count_in_cargo="0" count_in_hoarder="0" count_in_map="1" count_in_player="0" crafted="0" deloot="0"/>
	</type>		
	<type name="RS6_Avant_Camo_Blue">
		<nominal>0</nominal>
		<lifetime>3888000</lifetime>
		<restock>0</restock>
		<min>0</min>
		<quantmin>-1</quantmin>
		<quantmax>-1</quantmax>
		<cost>100</cost>
		<flags count_in_cargo="0" count_in_hoarder="0" count_in_map="1" count_in_player="0" crafted="0" deloot="0"/>
	</type>	
	<type name="RS6_Avant_Camo_Pink">
		<nominal>0</nominal>
		<lifetime>3888000</lifetime>
		<restock>0</restock>
		<min>0</min>
		<quantmin>-1</quantmin>
		<quantmax>-1</quantmax>
		<cost>100</cost>
		<flags count_in_cargo="0" count_in_hoarder="0" count_in_map="1" count_in_player="0" crafted="0" deloot="0"/>
	</type>	
	<type name="RS6_Avant_Camo_White">
		<nominal>0</nominal>
		<lifetime>3888000</lifetime>
		<restock>0</restock>
		<min>0</min>
		<quantmin>-1</quantmin>
		<quantmax>-1</quantmax>
		<cost>100</cost>
		<flags count_in_cargo="0" count_in_hoarder="0" count_in_map="1" count_in_player="0" crafted="0" deloot="0"/>
	</type>		
	<type name="RS6_Avant_Wheeel">
		<nominal>0</nominal>
		<lifetime>7200</lifetime>
		<restock>600</restock>
		<min>0</min>
		<quantmin>-1</quantmin>
		<quantmax>-1</quantmax>
		<cost>100</cost>
		<flags count_in_cargo="0" count_in_hoarder="0" count_in_map="1" count_in_player="0" crafted="0" deloot="0"/>
	</type>	
</types>